dreamkit/__init__.py
dreamkit/agent.py
dreamkit/agents/__init__.py
dreamkit/agents/models/__init__.py
dreamkit/agents/models/dreamerv3/__init__.py
dreamkit/agents/models/dreamerv3/dreamer.py
dreamkit/agents/models/dreamerv3/exploration.py
dreamkit/agents/models/dreamerv3/networks.py
dreamkit/agents/models/dreamerv3/world.py
dreamkit/envs/__init__.py
dreamkit/envs/atari.py
dreamkit/envs/crafter.py
dreamkit/envs/dmc.py
dreamkit/envs/dmlab.py
dreamkit/envs/memorymaze.py
dreamkit/envs/minecraft.py
dreamkit/envs/minecraft_base.py
dreamkit/envs/minecraft_minerl.py
dreamkit/envs/wrappers.py
dreamkit/envs/setup_scripts/__init__.py
dreamkit/utils/__init__.py
dreamkit/utils/parallel.py
dreamkit/utils/tools.py
dreamkit-0.1.0.dist-info/LICENSE
dreamkit-0.1.0.dist-info/METADATA
dreamkit-0.1.0.dist-info/WHEEL
dreamkit-0.1.0.dist-info/top_level.txt
dreamkit-0.1.0.dist-info/RECORD
