Metadata-Version: 2.1
Name: dreamkit
Version: 0.1.0
Summary: A toolkit for reinforcement learning research with Dreamerv3 using PyTorch.
Home-page: https://github.com/Andrew-Przy/dreamkit
Author: Andrew Przybilla
Author-email: andrewprzy@pm.me
Classifier: Programming Language :: Python :: 3
License-File: LICENSE
Requires-Dist: crafter ==1.8.0
Requires-Dist: dm-control ==1.0.9
Requires-Dist: einops ==0.3.0
Requires-Dist: gym ==0.22.0
Requires-Dist: matplotlib ==3.5.0
Requires-Dist: memory-maze ==1.0.3
Requires-Dist: moviepy ==1.0.3
Requires-Dist: mujoco ==2.3.5
Requires-Dist: numpy ==1.23.5
Requires-Dist: opencv-python ==4.7.0.72
Requires-Dist: protobuf ==3.20.0
Requires-Dist: ruamel.yaml ==0.17.4
Requires-Dist: tensorboard ==2.17.1
Requires-Dist: torch ==2.4.1
